veld_spec/README.md
veld_spec/__init__.py
veld_spec/dev.py
veld_spec/veld_spec.py
veld_spec-1.0.1.dist-info/LICENSE
veld_spec-1.0.1.dist-info/METADATA
veld_spec-1.0.1.dist-info/WHEEL
veld_spec-1.0.1.dist-info/top_level.txt
veld_spec-1.0.1.dist-info/RECORD
